{"title":"Combined feed","url":"https://MOVIECORD.github.io/news_drama/all.xml","elements":[{"title":"'연매살' 이서진부터 주현영, 대표의 사망으로 위기에 처하다 (다음 연예 ─ 뉴스 ─ 드라마)","contents":"OSEN","link":"https://v.daum.net/v/20221108132819713","retrieved":1667882252801},{"title":"신예은 “장르물 도전하고 싶었다, 노메이크업 출연” (다음 연예 ─ 뉴스 ─ 드라마)","contents":"스포츠동아","link":"https://v.daum.net/v/20221108131136344","retrieved":1667882252801},{"title":"신예은→로몬 '3인칭 복수', 이런 '고자극' 하이틴물 봤어? (다음 연예 ─ 뉴스 ─ 드라마)","contents":"OSEN","link":"https://v.daum.net/v/20221108123642846","retrieved":1667882252808},{"title":"신예은·로몬→이수민 '3인칭 복수', 신선함 가득한 하이틴 장르물 (다음 연예 ─ 뉴스 ─ 드라마)","contents":"엑스포츠뉴스","link":"https://v.daum.net/v/20221108122618617","retrieved":1667882252808},{"title":"김유진 감독 “‘3인칭 복수’, 기존 10대 학원물과는 다르다” (다음 연예 ─ 뉴스 ─ 드라마)","contents":"MK스포츠","link":"https://v.daum.net/v/20221108122402553","retrieved":1667882252809},{"title":"이정준 ‘꼭두의 계절’ 합류, 故이지한 후임된다 (다음 연예 ─ 뉴스 ─ 드라마)","contents":"뉴스엔","link":"https://v.daum.net/v/20221108122117499","retrieved":1667877707861},{"title":"김동욱X진기주 '어쩌다 마주친, 그대' 첫 대본 리딩 현장 (다음 연예 ─ 뉴스 ─ 드라마)","contents":"TV리포트","link":"https://v.daum.net/v/20221108122030484","retrieved":1667877707870},{"title":"“이런 고자극은 없었다”…‘3인칭 복수’ 신예은→로몬, 하이틴 복수 스릴러 (다음 연예 ─ 뉴스 ─ 드라마)","contents":"뉴스엔","link":"https://v.daum.net/v/20221108121455289","retrieved":1667877707878},{"title":"‘3인칭 복수’ 신예은 “사격에 부심 있어…자세 정말 좋다” (다음 연예 ─ 뉴스 ─ 드라마)","contents":"MK스포츠","link":"https://v.daum.net/v/20221108120608015","retrieved":1667877707880},{"title":"이수민 “예쁠 때 예쁜 역할 하고 싶어…겉모습 가꾸기 위해 노력” (다음 연예 ─ 뉴스 ─ 드라마)","contents":"뉴스엔","link":"https://v.daum.net/v/20221108120313906","retrieved":1667877707890},{"title":"'3인칭 복수' 서지훈 \"로몬, 액션씬 너무 잘 찍어…나보다 월등히 잘 했다\" (다음 연예 ─ 뉴스 ─ 드라마)","contents":"엑스포츠뉴스","link":"https://v.daum.net/v/20221108120241873","retrieved":1667877707890},{"title":"‘3인칭 복수’ 로몬 “신예은, 캐릭터와 싱크로율 130%” (다음 연예 ─ 뉴스 ─ 드라마)","contents":"MK스포츠","link":"https://v.daum.net/v/20221108120003596","retrieved":1667877707890},{"title":"\"이런 고자극 없었다\" 몰아치는 청불 하이틴 '3인칭 복수' (다음 연예 ─ 뉴스 ─ 드라마)","contents":"TV리포트","link":"https://v.daum.net/v/20221108115830544","retrieved":1667877707894},{"title":"'3인칭 복수' 고자극 장르물과 하이틴의 결합···재미 이상의 메시지 (다음 연예 ─ 뉴스 ─ 드라마)","contents":"서울경제","link":"https://v.daum.net/v/20221108115721492","retrieved":1667877707896},{"title":"신예은 “고된 모습 위해 화장 안 해…나인 줄 모른다면 성공” (다음 연예 ─ 뉴스 ─ 드라마)","contents":"뉴스엔","link":"https://v.daum.net/v/20221108115717488","retrieved":1667877707902}]}