{"title":"Combined feed","url":"https://MOVIECORD.github.io/news_drama/all.xml","elements":[{"title":"예를 갖춘 김민기 vs 절벽에 몸 던진 문상민…과제 승리는 누구에게 (다음 연예 ─ 뉴스 ─ 드라마)","contents":"뉴스엔","link":"https://v.daum.net/v/20221110095235899","retrieved":1668042251870},{"title":"‘뉴연플리’, OST 맛집 계보 잇는다..10CM 가창 참여 (다음 연예 ─ 뉴스 ─ 드라마)","contents":"OSEN","link":"https://v.daum.net/v/20221110095226889","retrieved":1668042251876},{"title":"'진검승부' 도경수, 하준과 의기투합해 김창완 서고 찾았다···10일 최종회 방송 (다음 연예 ─ 뉴스 ─ 드라마)","contents":"서울경제","link":"https://v.daum.net/v/20221110095207877","retrieved":1668042251877},{"title":"모닝커피, 13일 '태풍의 신부' OST '사랑을 했을까' 공개 (다음 연예 ─ 뉴스 ─ 드라마)","contents":"OSEN","link":"https://v.daum.net/v/20221110094055355","retrieved":1668042251878},{"title":"'금혼령' 박주현, 이토록 사랑스러운 사기꾼 궁합쟁이라니 (다음 연예 ─ 뉴스 ─ 드라마)","contents":"OSEN","link":"https://v.daum.net/v/20221110093942299","retrieved":1668042251883},{"title":"조문근, '내 눈에 콩깍지' OST '어느날 갑자기' 가창…10일 발매 (다음 연예 ─ 뉴스 ─ 드라마)","contents":"OSEN","link":"https://v.daum.net/v/20221110093740197","retrieved":1668042251884},{"title":"'환혼' part2는 3년 후..이재욱 부활→고윤정 등판? (다음 연예 ─ 뉴스 ─ 드라마)","contents":"OSEN","link":"https://v.daum.net/v/20221110093721191","retrieved":1668042251884},{"title":"'디 엠파이어' 김선아-신구-주세빈, 엄숙함 뒤에 품은 칼날 (다음 연예 ─ 뉴스 ─ 드라마)","contents":"OSEN","link":"https://v.daum.net/v/20221110093319003","retrieved":1668042251885},{"title":"'재벌집 막내아들' 신현빈, 송중기 인생 2회차 지원군 될까 (다음 연예 ─ 뉴스 ─ 드라마)","contents":"OSEN","link":"https://v.daum.net/v/20221110093211924","retrieved":1668042251886},{"title":"검사 신현빈, 송중기와 '특별한 관계성' 만든다 (다음 연예 ─ 뉴스 ─ 드라마)","contents":"스타뉴스","link":"https://v.daum.net/v/20221110093035849","retrieved":1668042251887},{"title":"도경수, 하준과 사이다 팀워크→김창완 숨통 조였다 (다음 연예 ─ 뉴스 ─ 드라마)","contents":"마이데일리","link":"https://v.daum.net/v/20221110091449052","retrieved":1668042251888},{"title":"'커튼콜' 강하늘, 진짜가 된 가짜…희대의 사기꾼일까 명배우일까 (다음 연예 ─ 뉴스 ─ 드라마)","contents":"OSEN","link":"https://v.daum.net/v/20221110091323996","retrieved":1668042251889},{"title":"‘재벌집 막내아들’ 신현빈, 풋풋함→카리스마 오가는 스틸 공개 (다음 연예 ─ 뉴스 ─ 드라마)","contents":"뉴스엔","link":"https://v.daum.net/v/20221110091212941","retrieved":1668042251891},{"title":"'진검승부' 도경수, 하준과 반전 공조…김창완에 총구 겨눴다 (다음 연예 ─ 뉴스 ─ 드라마)","contents":"엑스포츠뉴스","link":"https://v.daum.net/v/20221110091158919","retrieved":1668042251891},{"title":"최시원, 아버지 죽음 진실 밝혀졌다…이다희와 갈등 격화 (다음 연예 ─ 뉴스 ─ 드라마)","contents":"텐아시아","link":"https://v.daum.net/v/20221110085702320","retrieved":1668042251893}]}