{"title":"Combined feed","url":"https://MOVIECORD.github.io/news_drama/all.xml","elements":[{"title":"'그림자미녀' 심달기, 섬뜩한 미소로 비밀 품은 미스터리 서막 올랐다 (다음 연예 ─ 뉴스 ─ 드라마)","contents":"OSEN","link":"https://entertain.v.daum.net/v/20211102135946702","retrieved":1635829821797},{"title":"'백일의 낭군님' 이어 한번더!..옥택연x김혜윤 '어사와조이'를 기대하는 이유 (다음 연예 ─ 뉴스 ─ 드라마)","contents":"OSEN","link":"https://entertain.v.daum.net/v/20211102135926697","retrieved":1635829821797},{"title":"'오징어게임', 마의 연속 40일 넘었다..넷플릭스 전세계 1위ing (다음 연예 ─ 뉴스 ─ 드라마)","contents":"OSEN","link":"https://entertain.v.daum.net/v/20211102133219861","retrieved":1635829821797},{"title":"'연모' 박은빈, 로운-남윤수와 한밤 기습..최고 8.9% (다음 연예 ─ 뉴스 ─ 드라마)","contents":"엑스포츠뉴스","link":"https://entertain.v.daum.net/v/20211102132836744","retrieved":1635829821801},{"title":"'연모' 시청률 최고 8.9%..박은빈x로운x남윤수, 반격 작전 돌입 (다음 연예 ─ 뉴스 ─ 드라마)","contents":"OSEN","link":"https://entertain.v.daum.net/v/20211102131019329","retrieved":1635826459371},{"title":"'연모' 제작진 \"분노 유발자 박기웅, 악랄함 더 거세질 예정\" (다음 연예 ─ 뉴스 ─ 드라마)","contents":"뉴스엔","link":"https://entertain.v.daum.net/v/20211102130821282","retrieved":1635826459373},{"title":"몸풀기만 했을 뿐..'구경이', 이영애가 끌고 연출은 세련됐다 (다음 연예 ─ 뉴스 ─ 드라마)","contents":"OSEN","link":"https://entertain.v.daum.net/v/20211102130404197","retrieved":1635826459373},{"title":"하준 \"조여정과 두번째 호흡=신뢰 쌓여..하키x보드는 취미로 ing\" (다음 연예 ─ 뉴스 ─ 드라마)","contents":"OSEN","link":"https://entertain.v.daum.net/v/20211102123508768","retrieved":1635826459374},{"title":"'하이클래스' 하준 \"아이스하키, 대역없이 할 수 있을 정도로 연습\" (다음 연예 ─ 뉴스 ─ 드라마)","contents":"뉴스엔","link":"https://entertain.v.daum.net/v/20211102122636670","retrieved":1635826459375},{"title":"'하이클래스' 혼자여도 행복한 여자들 (다음 연예 ─ 뉴스 ─ 드라마)","contents":"뉴스엔","link":"https://entertain.v.daum.net/v/20211102121128406","retrieved":1635826459376},{"title":"'연모' 박은혜, 깊은 모성애로 로운 위로..맑고 따뜻한 케미 (다음 연예 ─ 뉴스 ─ 드라마)","contents":"OSEN","link":"https://entertain.v.daum.net/v/20211102120447232","retrieved":1635822710223},{"title":"'해피니스' 한효주 박형식 조우진, 적인지 편인지 모를 아슬한 공조 (다음 연예 ─ 뉴스 ─ 드라마)","contents":"뉴스엔","link":"https://entertain.v.daum.net/v/20211102120330217","retrieved":1635822710223},{"title":"류의현→미연 '어른연습생' 알 건 다 아는 Z세대들의 '노필터' 성장 연애담 (다음 연예 ─ 뉴스 ─ 드라마)","contents":"뉴스엔","link":"https://entertain.v.daum.net/v/20211102115706926","retrieved":1635822710223},{"title":"이준, '붉은 단심' 출연 확정..조선의 왕 이태役 (다음 연예 ─ 뉴스 ─ 드라마)","contents":"스타뉴스","link":"https://entertain.v.daum.net/v/20211102115204795","retrieved":1635822710226},{"title":"우현주 \"두 번의 암투병, 연기로 이겨냈죠\" (다음 연예 ─ 뉴스 ─ 드라마)","contents":"엑스포츠뉴스","link":"https://entertain.v.daum.net/v/20211102115024715","retrieved":1635822710228},{"title":"'아이돌' 안희연X김민규, 미묘한 기류...호기심↑ (네이버 TV연예 ─ 최신뉴스 ─ 드라마)","contents":"(엑스포츠뉴스 김수정 인턴기자) '아이돌' 안희연과 김민규 사이에 미묘한 기류가 포착되면서 호기심이 상승하고 있다. 오는 8일 첫 방송되는 JTBC 새 월화드라마 ‘IDOL '아이돌 : The Coup'’(이하 ‘아","link":"https://entertain.naver.com/now/read?oid=311&aid=0001367762","retrieved":1635829830588},{"title":"'어사와조이' 옥택연·김혜윤, 설렘 가득 순간 '포착' (네이버 TV연예 ─ 최신뉴스 ─ 드라마)","contents":"'어사와 조이' 옥택연, 김혜윤의 두근거리는 눈맞춤 순간이 공개됐다. 8일 방송되는 tvN 새 월화드라마 '어사와 조이' 측은 세상을 발칵 뒤집어 놓을 환장의 어사 콤비 옥택연, 김혜윤의 촬영장 비하인드 컷을 공개했","link":"https://entertain.naver.com/now/read?oid=015&aid=0004623575","retrieved":1635829830588},{"title":"'그림자미녀' 심달기, 섬뜩한 미소로 비밀 품은 미스터리 서막 올랐다 (네이버 TV연예 ─ 최신뉴스 ─ 드라마)","contents":"[OSEN=박판석 기자] ‘그림자 미녀’가 지난 1차 티저 영상에 이어 한층 더 강렬한 흡인력으로 무장한 메인 티저 영상을 공개, 기대감을 한층 더 끌어올린다. 오는 20일(토) 첫 공개되는 카카오TV 오리지널 ‘그","link":"https://entertain.naver.com/now/read?oid=109&aid=0004502864","retrieved":1635829830590},{"title":"'백일의 낭군님' 이어 한번더!..옥택연x김혜윤 '어사와조이'를 기대하는 이유 (네이버 TV연예 ─ 최신뉴스 ─ 드라마)","contents":"[OSEN=박소영 기자] ‘어사와 조이’ 옥택연, 김혜윤이 바라만 봐도 두근거리는 케미스트리로 설렘을 선사한다. 오는 11월 8일 방송되는 tvN 15주년 특별기획 월화드라마 ‘어사와 조이’(연출 유종선, 극본 이재","link":"https://entertain.naver.com/now/read?oid=109&aid=0004502863","retrieved":1635829830594},{"title":"손소망, '너와 나의 경찰수업' 출연…강다니엘·채수빈과 호흡 (네이버 TV연예 ─ 최신뉴스 ─ 드라마)","contents":"(엑스포츠뉴스 김예은 기자) 배우 손소망이 새 드라마로 안방극장을 찾아간다. 2일 소속사 메이저나인은 \"손소망이 2022년 상반기 공개 예정인 디즈니+의 오리지널 시리즈 '너와 나의 경찰수업'에 출연을 확정했다\"라고","link":"https://entertain.naver.com/now/read?oid=311&aid=0001367758","retrieved":1635829830597},{"title":"'연모' 박은빈-로운-남윤수, 박기웅 향한 반격..한밤 기습 현장 (네이버 TV연예 ─ 최신뉴스 ─ 드라마)","contents":"'연모' 박은빈이 로운, 남윤수와 함께 반격에 돌입한다. 지난 1일 방영된 KBS 2TV 월화드라마 '연모'(연출 송현욱, 이현석, 극본 한희정, 제작 이야기사냥꾼, 몬스터유니온) 7회 시청률은 전국 7%(닐슨코리아","link":"https://entertain.naver.com/now/read?oid=108&aid=0003001499","retrieved":1635829830600},{"title":"박은빈X로운X남윤수, 반격 작전 돌입?…한밤 기습 현장 포착 ('연모') (네이버 TV연예 ─ 최신뉴스 ─ 드라마)","contents":"[텐아시아=차혜영 기자] ‘연모’ 시청률이 분당 최고 8.9%까지 치솟는 등 상승세를 보인 가운데, 박은빈이 로운, 남윤수와 함께 반격에 돌입, 기대를 더한다. 지난 1일 방영된 KBS 2TV 월화드라마 ‘연모’ 7","link":"https://entertain.naver.com/now/read?oid=312&aid=0000509014","retrieved":1635829830604},{"title":"'연모' 박은빈, 로운-남윤수와 한밤 기습...최고 8.9% [종합] (네이버 TV연예 ─ 최신뉴스 ─ 드라마)","contents":"(엑스포츠뉴스 김수정 인턴기자) ‘연모’ 박은빈이 로운-남윤수와 함께 한밤 기습하는 장면이 포착됐다. 지난 1일 방영된 KBS 2TV 월화드라마 ‘연모’ 7회 시청률은 전국 7%로 자체 최고 기록을 경신했다. (닐슨","link":"https://entertain.naver.com/now/read?oid=311&aid=0001367748","retrieved":1635829830604},{"title":"옥택연x김혜윤, 조선팔도 제일의 비주얼 커플로 설렘 케미 (‘어서와 조이’) (네이버 TV연예 ─ 최신뉴스 ─ 드라마)","contents":"[텐아시아=류정민 기자] ‘어사와 조이’ 옥택연, 김혜윤이 바라만 봐도 두근거리는 케미스트리로 안방 극장에 설렘을 선사한다. 오는 8일 방송되는 tvN 15주년 특별기획 월화드라마 ‘어사와 조이’측은 2일, 세상을","link":"https://entertain.naver.com/now/read?oid=312&aid=0000509010","retrieved":1635829830608},{"title":"김차윤, '학교 2021' 출연...서희선과 앙숙 케미 (네이버 TV연예 ─ 최신뉴스 ─ 드라마)","contents":"(엑스포츠뉴스 김수정 인턴기자) 신예 김차윤이 ‘학교 2021’에 출연한다. KBS 2TV 수목드라마 ‘학교 2021’은 입시경쟁이 아닌 다른 길을 선택한 아이들, 모호한 경계에 놓인 열여덟 청춘들의 꿈·우정·설렘의","link":"https://entertain.naver.com/now/read?oid=311&aid=0001367741","retrieved":1635829830611},{"title":"'어사와 조이' 옥택연, 설렘 유발 비하인드…'열정모드 ON' (네이버 TV연예 ─ 최신뉴스 ─ 드라마)","contents":"(엑스포츠뉴스 하지원 기자) ‘어사와 조이’ 옥택연, 김혜윤이 바라만 봐도 두근거리는 케미스트리로 설렘을 선사한다. 8일 방송되는 tvN 15주년 특별기획 월화드라마 ‘어사와 조이’ 측은 2일, 세상을 발칵 뒤집어","link":"https://entertain.naver.com/now/read?oid=311&aid=0001367740","retrieved":1635826467554},{"title":"민도희, 디즈니+ '너와 나의 경찰수업' 합류 [공식입장] (네이버 TV연예 ─ 최신뉴스 ─ 드라마)","contents":"(엑스포츠뉴스 김예은 기자) 배우 민도희가 경찰대 신입생으로 변신한다. 2022년 상반기 공개 예정인 디즈니+의 오리지널 시리즈 ‘너와 나의 경찰수업’은 경찰대학을 배경으로 우리가 응원하고 싶은 청춘들의 사랑과 도전","link":"https://entertain.naver.com/now/read?oid=311&aid=0001367738","retrieved":1635826467556},{"title":"'연모' 시청률 최고 8.9%…박은빈x로운x남윤수, 반격 작전 돌입 (네이버 TV연예 ─ 최신뉴스 ─ 드라마)","contents":"[OSEN=장우영 기자] ‘연모’ 시청률이 분당 최고 8.9%까지 치솟는 등 상승세를 보인 가운데, 박은빈이 로운, 남윤수와 함께 반격에 돌입, 기대를 더한다. 지난 1일 방영된 KBS2 월화드라마 ‘연모’(극본 한","link":"https://entertain.naver.com/now/read?oid=109&aid=0004502834","retrieved":1635826467556},{"title":"'연모' 제작진 \"분노 유발자 박기웅, 악랄함 더 거세질 예정\" (네이버 TV연예 ─ 최신뉴스 ─ 드라마)","contents":"[뉴스엔 김명미 기자] '연모' 박은빈이 로운, 남윤수와 함께 반격에 돌입, 기대를 더한다. 11월 1일 방영된 KBS 2TV 월화드라마 ‘연모’(연출 송현욱, 이현석, 극본 한희정, 제작 이야기사냥꾼, 몬스터유니온","link":"https://entertain.naver.com/now/read?oid=609&aid=0000506566","retrieved":1635826467556},{"title":"조여정, 마지막까지 눈부신 열연…애정가득 대본 인증샷 (‘하이클래스’) (네이버 TV연예 ─ 최신뉴스 ─ 드라마)","contents":"[텐아시아=류정민 기자] '하이클래스' 조여정이 마지막 회차까지 눈부신 열연으로 유종의 미를 장식했다. 조여정은 지난 1일 종영한 tvN 월화드라마 ‘하이클래스’에서 남편의 죽음으로 하루아침에 악몽같이 변해 버린 삶","link":"https://entertain.naver.com/now/read?oid=312&aid=0000509008","retrieved":1635826467557},{"title":"몸풀기만 했을 뿐..'구경이', 이영애가 끌고 연출은 세련됐다 [Oh!쎈 레터] (네이버 TV연예 ─ 최신뉴스 ─ 드라마)","contents":"[OSEN=하수정 기자] 이영애의 컴백작으로 주목받은 '구경이'가 첫 방송을 마쳤다. 기대를 저버리지 않은 이영애의 연기와 세련된 연출 등이 다음 회를 기다리게 했다. 지난 10월 30일 방송된 '구경이'(연출 이정","link":"https://entertain.naver.com/now/read?oid=109&aid=0004502832","retrieved":1635826467557},{"title":"'하이클래스' 조여정 \"좋은 배우·제작진과 함께해 감사\" 종영 소감 (네이버 TV연예 ─ 최신뉴스 ─ 드라마)","contents":"(엑스포츠뉴스 하지원 기자) '하이클래스' 조여정이 눈부신 열연으로 유종의 미를 장식했다. 조여정은 지난 1일 종영한 tvN 월화드라마 ‘하이클래스'에서 남편의 죽음으로 하루아침에 악몽같이 변해 버린 삶, 아들을 지","link":"https://entertain.naver.com/now/read?oid=311&aid=0001367735","retrieved":1635826467567},{"title":"‘스폰서’ 구자성, 첫 스틸 공개…따뜻함-차가움 오가는 묘한 아우라 (네이버 TV연예 ─ 최신뉴스 ─ 드라마)","contents":"배우 구자성이 ‘스폰서’를 통해 야망으로 가득 찬 캐릭터를 그려나간다. 오는 29일 첫 방송되는 새 월화드라마 ‘스폰서’(연출 이철 / 극본 한희정 / 제작 빅토리콘텐츠) 측은 훈훈한 매력을 가감 없이 발휘하는 구자","link":"https://entertain.naver.com/now/read?oid=410&aid=0000827937","retrieved":1635826467568},{"title":"‘통증의 풍경’ 안내상·백지원, 심리전부터 범행 막기 위한 고군분투까지 (네이버 TV연예 ─ 최신뉴스 ─ 드라마)","contents":"‘통증의 풍경’이 음산한 분위기가 물씬 풍기는 방송 예고 영상을 공개, 예비 시청자들의 뜨거운 반응을 얻고 있다. 오는 11월 5일 방송 예정인 UHD KBS 드라마 스페셜 2021-TV 시네마 ‘통증의 풍경’(연출","link":"https://entertain.naver.com/now/read?oid=410&aid=0000827936","retrieved":1635826467570},{"title":"이준·강한나·장혁, ‘붉은 단심’ 출연 확정 (네이버 TV연예 ─ 최신뉴스 ─ 드라마)","contents":"배우 이준, 강한나, 장혁이 ‘붉은 단심’에 출연한다. KBS2 새 월화드라마 ‘붉은 단심’(연출 유영은/ 극본 박필주/ 제작 지앤지프로덕션(주))은 반정으로 왕이 된 선종, 그 뒤를 이어 조선의 왕이 된 이태(이준 분","link":"https://entertain.naver.com/now/read?oid=410&aid=0000827934","retrieved":1635826467574},{"title":"'하이클래스' 하준 \"아이스하키, 대역없이 할 수 있을 정도로 연습\"(일문일답) (네이버 TV연예 ─ 최신뉴스 ─ 드라마)","contents":"[뉴스엔 박수인 기자] 배우 하준이 ‘하이클래스’ 종영소감을 전했다. 하준은 11월 1일 종영한 tvN 월화드라마 ‘하이클래스’(연출 최병길 극본 스토리홀릭)에서 HSC 국제 학교의 체육교사 대니오와 흥신소 사장인","link":"https://entertain.naver.com/now/read?oid=609&aid=0000506549","retrieved":1635826467574},{"title":"‘청와대로 간다’ 감독 “김성령→이학주, 싱크로율은 100% 그 이상” (네이버 TV연예 ─ 최신뉴스 ─ 드라마)","contents":"‘이렇게 된 이상 청와대로 간다’의 윤성호 감독이 김성령, 배해선, 백현진, 이학주의 캐릭터 싱크로율에 대한 생각과 애정 어린 메시지를 전했다. 오는 11월 12일 오전 11시 전편 공개되는 웨이브(wavve) 오리","link":"https://entertain.naver.com/now/read?oid=410&aid=0000827931","retrieved":1635826467575},{"title":"트레저, 새 웹드라마 ‘남고괴담’ 단체 메인 포스터 공개 (네이버 TV연예 ─ 최신뉴스 ─ 드라마)","contents":"[OSEN=장우영 기자] YG 대형 그룹 트레저가 오싹한 기운이 감도는 '남고괴담'으로 글로벌 팬들을 초대했다. YG엔터테인먼트는 2일 공식 블로그에 트레저의 새 웹드라마 '남고괴담' 메인 포스터를 게재했다. 어두운","link":"https://entertain.naver.com/now/read?oid=109&aid=0004502824","retrieved":1635826467575},{"title":"'하이클래스' 혼자여도 행복한 여자들 [TV와치] (네이버 TV연예 ─ 최신뉴스 ─ 드라마)","contents":"[뉴스엔 박정민 기자] '하이클래스'가 혼자여도 행복한 여자들의 이야기를 담았다. 11월 1일 방송된 tvN 월화드라마 '하이클래스'(극본 스토리홀릭/연출 최병길) 마지막 회에서는 행복에 대한 답을 찾아가는 인물들의","link":"https://entertain.naver.com/now/read?oid=609&aid=0000506543","retrieved":1635826467575},{"title":"'연모' 박은혜, 깊은 모성애로 로운 위로…맑고 따뜻한 케미 (네이버 TV연예 ─ 최신뉴스 ─ 드라마)","contents":"[OSEN=장우영 기자] 박은혜가 남다른 모성애로 안방극장을 뭉클하게 했다. 1일 방송된 KBS2 ‘연모’ 7회에는 삼개방으로 인한 파직 위기에서 막 벗어난 지운(로운 분)과 그를 걱정하는 어머니 김씨부인(박은혜)의","link":"https://entertain.naver.com/now/read?oid=109&aid=0004502821","retrieved":1635822718172}]}