{"title":"다음 연예 ─ 뉴스 ─ 드라마","url":"https://entertain.daum.net/news/drama","favicon":"https://entertain.daum.net/news/favicon.ico","elements":[{"title":"송채환 9년만→이윤성 12년만 컴백, ‘금이야 옥이야’ 든든한 라인업","contents":"뉴스엔","link":"https://v.daum.net/v/20230324094508379","retrieved":1679618987944},{"title":"이지아 이젠 한수연 살해범 찾기, 박기웅 용의자로 몰려","contents":"스포츠동아","link":"https://v.daum.net/v/20230324094054225","retrieved":1679618987944},{"title":"이선호, 단호함에 스윗함 추가 '오빠美'","contents":"스타뉴스","link":"https://v.daum.net/v/20230324093235932","retrieved":1679618987945},{"title":"최자혜 3년만 컴백, 도도한 재벌 2세 강렬 변신","contents":"뉴스엔","link":"https://v.daum.net/v/20230324093021870","retrieved":1679618987945},{"title":"'더글로리' 차주영 \"'스튜어디스 혜정이'라고 불리는 것 정말 좋아\"","contents":"이데일리","link":"https://v.daum.net/v/20230324092805780","retrieved":1679618987948},{"title":"‘꽃선비’ 측 “로맨스 미스터리 차곡차곡 빌드업, 재미 감동 전율 전할 것”","contents":"뉴스엔","link":"https://v.daum.net/v/20230324092525690","retrieved":1679618987951},{"title":"'성스러운 아이돌' 고보결 \"살 찌운 덕분에 귀여워졌다\"","contents":"MBC연예","link":"https://v.daum.net/v/20230324092408640","retrieved":1679618987951},{"title":"이장우, 복수보단 사랑 선택 \"순정남 그 자체\"","contents":"마이데일리","link":"https://v.daum.net/v/20230324092252600","retrieved":1679618987957},{"title":"'방과 후 전쟁활동' 감독·작가진이 제시한 시청 포인트는?","contents":"이데일리","link":"https://v.daum.net/v/20230324091546351","retrieved":1679618987957},{"title":"고보결 “살 찌운 덕에 귀여운 이미지 만들어져”","contents":"뉴스엔","link":"https://v.daum.net/v/20230324091244248","retrieved":1679618987958},{"title":"팽팽한 기싸움..박형식vs정웅인, '청춘월담' 긴장감 높인 권력 전쟁","contents":"스포츠조선","link":"https://v.daum.net/v/20230324091106188","retrieved":1679618987958},{"title":"‘나쁜엄마’ 라미란X이도현, 인생 리부트 메인 포스터 공개","contents":"뉴스엔","link":"https://v.daum.net/v/20230324090625048","retrieved":1679618987958},{"title":"한수연 누가 죽였나? “타운하우스 발칵, 관계변화 요동친다”","contents":"뉴스엔","link":"https://v.daum.net/v/20230324090439998","retrieved":1679618987959},{"title":"장혁 \"장나라, 서로에 당연하게 반응…찰떡궁합\" 4번째 호흡 자랑","contents":"엑스포츠뉴스","link":"https://v.daum.net/v/20230324085016537","retrieved":1679618987960},{"title":"달라도 너무 다른 우도환X김지연X차학연 묘한 인연","contents":"뉴스엔","link":"https://v.daum.net/v/20230324084420348","retrieved":1679618987962}]}