{"title":"다음 연예 ─ 뉴스 ─ 드라마","url":"https://entertain.daum.net/news/drama","favicon":"https://entertain.daum.net/news/favicon.ico","elements":[{"title":"서예지 지운 '아일랜드', 이다희에겐 간절했던 인생작","contents":"OSEN","link":"https://v.daum.net/v/20221222175119898","retrieved":1671700216167},{"title":"'마녀의 게임' 김규선, '사이다 복수' 휘몰아칠까 \"기대하셔도 좋아요\"","contents":"OSEN","link":"https://v.daum.net/v/20221222174343688","retrieved":1671700216168},{"title":"\"배우로서 갓 태어난 느낌\"…다음이 더 기대되는 김현진의 '치얼업'","contents":"SBS연예뉴스","link":"https://v.daum.net/v/20221222173919571","retrieved":1671700216168},{"title":"'귀못' 감독 \"박하나, 입수 장면 모두 직접 소화할 정도로 열의\"","contents":"스타뉴스","link":"https://v.daum.net/v/20221222173704502","retrieved":1671700216178},{"title":"'일당백집사' 종영 D-day, 이혜리X이준영 '집사커플' 마지막 미션 뭐길래","contents":"OSEN","link":"https://v.daum.net/v/20221222172225961","retrieved":1671700216178},{"title":"'썸바디''오매라' 제작 정아름 대표 \"주 단위 행복 전해주고파\"","contents":"연합뉴스","link":"https://v.daum.net/v/20221222171726767","retrieved":1671700216178},{"title":"'양들의 침묵' 김새벽, 乙들의 침묵 깨며 위태로운 고발…묵직한 메시지","contents":"OSEN","link":"https://v.daum.net/v/20221222171437692","retrieved":1671700216178},{"title":"안내상 ♥ 날리고 난리→채종협 효도 플렉스","contents":"스포츠동아","link":"https://v.daum.net/v/20221222170647419","retrieved":1671696815544},{"title":"'재벌집 막내아들' 박지현 \"김남희와 결혼식, 연기하며 화났다\"","contents":"OSEN","link":"https://v.daum.net/v/20221222170624409","retrieved":1671696815548},{"title":"\"장르물 이미 차고 넘쳐\"…김남길·이다희·차은우 '아일랜드', 차별점은 '제주도'","contents":"텐아시아","link":"https://v.daum.net/v/20221222170101224","retrieved":1671696815550},{"title":"박하나, 금기 깬 욕망…'귀못' 오늘 공개","contents":"OSEN","link":"https://v.daum.net/v/20221222165541030","retrieved":1671696815550},{"title":"황석희 ‘갱스 오브 런던’ 시즌2 번역 “11년 만 드라마 작업, 설레기도”","contents":"뉴스엔","link":"https://v.daum.net/v/20221222165205950","retrieved":1671696815550},{"title":"정소민 없어서 안 될 줄..'환혼' 파트2, 4회 만에 두자릿수 시청률 비결","contents":"OSEN","link":"https://v.daum.net/v/20221222163558432","retrieved":1671696815550},{"title":"'커튼콜' 고두심, 거목같은 뿌리깊은 연기력 \"시청자 울린 명연기\"","contents":"마이데일리","link":"https://v.daum.net/v/20221222162942203","retrieved":1671696815550},{"title":"김신록♥김도현 미방 키스신→김남희♥박지현 결혼식 비하인드 공개","contents":"텐아시아","link":"https://v.daum.net/v/20221222162602066","retrieved":1671696815550}]}