{"title":"다음 연예 ─ 뉴스 ─ 드라마","url":"https://entertain.daum.net/news/drama","favicon":"https://entertain.daum.net/news/favicon.ico","elements":[{"title":"‘우당탕탕 패밀리’ 이도겸, 남상지 직업 알았다","contents":"MK스포츠","link":"https://v.daum.net/v/20231108093903752","retrieved":1699404174850},{"title":"4년째 똑같은 연기 이제 그만…김동욱, 낯설지만 반가운 도전","contents":"텐아시아","link":"https://v.daum.net/v/20231108093802708","retrieved":1699404174858},{"title":"씨름 신동 장동윤 ENA 살리나..'모래에도 꽃이 핀다' 12월 20일 첫방","contents":"OSEN","link":"https://v.daum.net/v/20231108093735696","retrieved":1699404174859},{"title":"'운수 오진 날' 이성민X유연석X이정은, ‘3인 3색’ 3차 포스터 공개","contents":"OSEN","link":"https://v.daum.net/v/20231108093723690","retrieved":1699404174860},{"title":"'낮에 뜨는 달' 김영대 경호원 된 표예진, 첫날부터 일촉즉발 위기","contents":"OSEN","link":"https://v.daum.net/v/20231108093627644","retrieved":1699404174860},{"title":"범죄자 처단하는 남주혁, 뒤쫓는 김소진…'비질란테' 오늘 공개","contents":"엑스포츠뉴스","link":"https://v.daum.net/v/20231108093434569","retrieved":1699404174862},{"title":"김유정X송강, 화보급 캐릭터 포스터 눈길…레전드 비주얼 커플 탄생","contents":"엑스포츠뉴스","link":"https://v.daum.net/v/20231108093048407","retrieved":1699404174863},{"title":"'하이쿠키' 판매 나선 남지현, '쿠키' 비밀 알아낼까","contents":"OSEN","link":"https://v.daum.net/v/20231108093018381","retrieved":1699404174863},{"title":"김유정·송강, 캐릭터 포스터가 화보급..레전드 로판 비주얼","contents":"OSEN","link":"https://v.daum.net/v/20231108092721276","retrieved":1699404174864},{"title":"장동윤→이주승, 모래판서 청춘 로코 꽃피운다…'모래에도 꽃이 핀다', 12월 20일 첫방송","contents":"스포츠조선","link":"https://v.daum.net/v/20231108092701259","retrieved":1699404174865},{"title":"김중돈 ‘고려 거란 전쟁’ 숨겨진 영웅 활약 “정통사극 첫 도전”","contents":"뉴스엔","link":"https://v.daum.net/v/20231108092550219","retrieved":1699404174866},{"title":"장동윤→이주명 설레는 청춘들 온다 ‘모래에도 꽃이 핀다’ 12월 20일 첫방","contents":"뉴스엔","link":"https://v.daum.net/v/20231108091910017","retrieved":1699404174867},{"title":"상속녀 김유정·악마 송강, 서로에게 홀린 듯…의미심장","contents":"텐아시아","link":"https://v.daum.net/v/20231108091901013","retrieved":1699404174868},{"title":"김유정 악마 송강에 내민 손, 십자가 타투 의미는?","contents":"뉴스엔","link":"https://v.daum.net/v/20231108091320795","retrieved":1699404174869},{"title":"표예진, 김영대 경호 첫날부터 일촉즉발 사고","contents":"뉴스엔","link":"https://v.daum.net/v/20231108090746587","retrieved":1699404174871}]}