{"title":"다음 연예 ─ 뉴스 ─ 드라마","url":"https://entertain.daum.net/news/drama","favicon":"https://entertain.daum.net/news/favicon.ico","elements":[{"title":"'파친코'→'돼지의 왕', 넷플릭스 공백 메울 OTT 기대작들","contents":"스포츠서울","link":"https://entertain.v.daum.net/v/20220325060003874","retrieved":1648156277501},{"title":"'서른, 아홉' 손예진, 빚쟁이 찾아오자 친모와 관계 정리 결심","contents":"엑스포츠뉴스","link":"https://entertain.v.daum.net/v/20220325005001606","retrieved":1648138494372},{"title":"'서른, 아홉' 손예진, 친母 빚 탕감 요구에 눈물→전미도, 직접 추모원 예약","contents":"스타뉴스","link":"https://entertain.v.daum.net/v/20220325004213559","retrieved":1648138494374},{"title":"'서른아홉' 죽음 앞둔 전미도, ♥이무생 데리고 직접 추모원 예약","contents":"MBC연예","link":"https://entertain.v.daum.net/v/20220325000553998","retrieved":1648134766068},{"title":"'킬힐' 김하늘, 깜짝 출연..정의제, 이혜영 지시 안 따랐다","contents":"스타뉴스","link":"https://entertain.v.daum.net/v/20220324235233688","retrieved":1648134766070},{"title":"'서른, 아홉' 손예진, 친모 돈 요구에 분노→전미도, 납골당 찾아 마지막 준비","contents":"TV리포트","link":"https://entertain.v.daum.net/v/20220324234330596","retrieved":1648134766071},{"title":"'서른, 아홉' 전미도, 이무생 子와 만남 \"아빠 친구야\"","contents":"스타뉴스","link":"https://entertain.v.daum.net/v/20220324234055584","retrieved":1648134766072},{"title":"'서른, 아홉' 손예진, 안소희 입양 아픔 위로 \"연우진 父 별로더라\"","contents":"엑스포츠뉴스","link":"https://entertain.v.daum.net/v/20220324232026392","retrieved":1648134766073},{"title":"'서른, 아홉' 손예진 \"돈 있다고 줄리어드 못가. 사망 친부모 DNA\" 안소희 위로","contents":"스포츠서울","link":"https://entertain.v.daum.net/v/20220324231936381","retrieved":1648134766074},{"title":"임시완, 팬 손예진에 사인..'시한부' 전미도와 포옹","contents":"MBC연예","link":"https://entertain.v.daum.net/v/20220324231552335","retrieved":1648134766085},{"title":"'서른, 아홉' 손예진X김지현, 전미도 첫 촬영장 방문..임시완 보고 '환호'","contents":"스타뉴스","link":"https://entertain.v.daum.net/v/20220324230724276","retrieved":1648131102125},{"title":"'킬힐' 김하늘, 후배들 앞에서 모멸감 준 김효선 응징 \"난 너의 가치를 뜯어낼 수 있어\"","contents":"TV리포트","link":"https://entertain.v.daum.net/v/20220324225800145","retrieved":1648131102125},{"title":"'킬힐' 김재철X한수연, 쇼윈도 부부..사업 확장 안 하자 발끈","contents":"스타뉴스","link":"https://entertain.v.daum.net/v/20220324225745142","retrieved":1648131102125},{"title":"'서른, 아홉' 임시완, 전미도 상대 배우로 카메오 '애틋 포옹'","contents":"엑스포츠뉴스","link":"https://entertain.v.daum.net/v/20220324225629129","retrieved":1648131102126},{"title":"'킬힐' 김하늘 \"남편 김진우에 대한 마음 이미 떴다..사랑은 아냐\"","contents":"스타뉴스","link":"https://entertain.v.daum.net/v/20220324223800791","retrieved":1648131102127}]}