{"title":"다음 연예 ─ 뉴스 ─ 드라마","url":"https://entertain.daum.net/news/drama","favicon":"https://entertain.daum.net/news/favicon.ico","elements":[{"title":"이선균, 박훈에 솔깃한 제안…\"김홍파 무릎 꿇게 만들 수 있어\"","contents":"엑스포츠뉴스","link":"https://v.daum.net/v/20230128070019954","retrieved":1674857421397},{"title":"'법쩐' 이선균, \"당신 앞에 김홍파가 무릎꿇게 해주겠다\"…박훈에 거래 제안","contents":"SBS연예뉴스","link":"https://v.daum.net/v/20230128070005922","retrieved":1674857421397},{"title":"'꼭두의 계절' 임수향, 김정현과 그린라이트 기대했지만… 갑작스런 사망→부활 '충격'","contents":"OSEN","link":"https://v.daum.net/v/20230128065424880","retrieved":1674857421398},{"title":"'법쩐' 이선균, \"잘 들어, 주인이 누군지 알려줄게\"…교도관, 무릎 꿇었다","contents":"SBS연예뉴스","link":"https://v.daum.net/v/20230128032701925","retrieved":1674846531634},{"title":"이적, 29일 전도연·정경호 ‘일타 스캔들’ OST 발표","contents":"스포츠동아","link":"https://v.daum.net/v/20230128010010530","retrieved":1674836012305},{"title":"문채원, 의식불명에서 깨어났다…이선균 변호사로 등장","contents":"엑스포츠뉴스","link":"https://v.daum.net/v/20230127235006170","retrieved":1674832285605},{"title":"첫방 '꼭두의 계절' 김정현, 사망→꼭두로 부활? 임수향 목 조르며 \"죽여버려\"","contents":"OSEN","link":"https://v.daum.net/v/20230127232045959","retrieved":1674832285606},{"title":"'꼭두의 계절' 임수향, 자기 못 알아본 김정현에 \"쌍둥이세요?\"","contents":"스타뉴스","link":"https://v.daum.net/v/20230127230153894","retrieved":1674828608181},{"title":"이선균, 교도관 이용해 권력 얻었다…\"얼마든지 지옥으로 보낼 수 있어\"","contents":"엑스포츠뉴스","link":"https://v.daum.net/v/20230127225550871","retrieved":1674828608182},{"title":"'꼭두의 계절' 김정현, 임수향에 \"낙하산은 싫은 가요?\"","contents":"스타뉴스","link":"https://v.daum.net/v/20230127224025758","retrieved":1674828608184},{"title":"이선균, 과거 김홍파 작전주 눈치챘다…\"누나 돈까지 싹 담그고\"","contents":"엑스포츠뉴스","link":"https://v.daum.net/v/20230127223500694","retrieved":1674828608189},{"title":"\"낙하산 싫어?\" '꼭두의 계절' 임수향, 김정현 선택 받고 면접 합격!","contents":"OSEN","link":"https://v.daum.net/v/20230127222608572","retrieved":1674828608196},{"title":"첫방 '꼭두의 계절' 임수향, 벚꽃 잎 속 김정현과 설레는 '첫 만남'","contents":"스타뉴스","link":"https://v.daum.net/v/20230127222416567","retrieved":1674828608202},{"title":"‘그때 그곳’에서 복귀한 김정현, 5년 전과 어떻게 달라졌나?","contents":"OSEN","link":"https://v.daum.net/v/20230127204117321","retrieved":1674821905837},{"title":"박하나, 친母 지수원 감금 알았다…\"엄마 여깄어\" 울컥","contents":"엑스포츠뉴스","link":"https://v.daum.net/v/20230127203543240","retrieved":1674821905837}]}