{"title":"다음 연예 ─ 뉴스 ─ 드라마","url":"https://entertain.daum.net/news/drama","favicon":"https://entertain.daum.net/news/favicon.ico","elements":[{"title":"'미녀와 순정남' 이일화X지현우, 김혜선에 母子 관계 들통","contents":"엑스포츠뉴스","link":"https://v.daum.net/v/20240708061002373","retrieved":1720386681943},{"title":"엄효섭 첫등장, 김혜선 포옹 과거사진 고윤 출생비밀 있나","contents":"뉴스엔","link":"https://v.daum.net/v/20240708060658353","retrieved":1720386681944},{"title":"“마음대로 살 거” 한수아 가출, 클럽 갔다가 지현우에 혼쭐","contents":"뉴스엔","link":"https://v.daum.net/v/20240708060643350","retrieved":1720386681944},{"title":"김혜선, 지현우 출생비밀 알고 이일화♥박상원 이혼시키나","contents":"뉴스엔","link":"https://v.daum.net/v/20240708060631349","retrieved":1720386681945},{"title":"“어머니가 달라 거칠어” 정문성, 신하균에 진구 험담","contents":"뉴스엔","link":"https://v.daum.net/v/20240708060601344","retrieved":1720386681945},{"title":"진구 악역 아니었나? 신하균에 사과→조아람에 “꼬맹이” 반전","contents":"뉴스엔","link":"https://v.daum.net/v/20240708060545341","retrieved":1720386681946},{"title":"\"이건 실수 아니에요\"…'낮밤녀' 정은지, ♥최진혁에 기습 첫 키스","contents":"엑스포츠뉴스","link":"https://v.daum.net/v/20240708000747253","retrieved":1720365080547},{"title":"\"실수 아니에요\" 정은지, 최진혁에 '직진' 입맞춤··로맨스 '급물살' 탈까","contents":"OSEN","link":"https://v.daum.net/v/20240708000021074","retrieved":1720365080547},{"title":"한보름, 현대판 백설공주? 복수의 여신!","contents":"OSEN","link":"https://v.daum.net/v/20240707234656973","retrieved":1720365080548},{"title":"‘낮과 밤이 다른 그녀’ 최진혁, 정은지와 취중진담 “고아라는 사실 상관없다는 말… 그날은 좋았다”","contents":"MBC연예","link":"https://v.daum.net/v/20240707234559969","retrieved":1720365080549},{"title":"\"걱정 마요\" 백서후, 정은지 지키겠다 선언... 아이돌의 순애보","contents":"TV리포트","link":"https://v.daum.net/v/20240707233830947","retrieved":1720365080556},{"title":"정은지, '신체 비밀' 알아챈 백서후에 정색 \"어떻게 알았냐고요\"","contents":"OSEN","link":"https://v.daum.net/v/20240707233123922","retrieved":1720365080556},{"title":"'낮과 밤이 다른 그녀' 정은지, 백서후에 비밀 들킨 것 알고 '충격'","contents":"엑스포츠뉴스","link":"https://v.daum.net/v/20240707231524854","retrieved":1720365080558},{"title":"\"뭐가 어떻게 된 거야\" 최진혁, 정은지 쓰러지자 '예민미' 폭발","contents":"OSEN","link":"https://v.daum.net/v/20240707231019822","retrieved":1720365080560},{"title":"“모가지 잘라버릴 것…” 신하균, 진구와 美친 대립→JU건설 비리 밝혔다","contents":"OSEN","link":"https://v.daum.net/v/20240707230645790","retrieved":1720361358065}]}