{"title":"다음 연예 ─ 뉴스 ─ 드라마","url":"https://entertain.daum.net/news/drama","favicon":"https://entertain.daum.net/news/favicon.ico","elements":[{"title":"이유미, 정우 '노메달 클럽' 입성..숨겨온 감정 폭발","contents":"엑스포츠뉴스","link":"https://v.daum.net/v/20220913130926545","retrieved":1663042499799},{"title":"'복학생' 노종현, 이런 남사친 어디 없나요? '찐절친 끝판왕'","contents":"OSEN","link":"https://v.daum.net/v/20220913124916136","retrieved":1663042499800},{"title":"'오징어게임' 에미상 이정재 남우주연상·황동혁 감독상 수상 '한국·비영어권 최초'","contents":"텐아시아","link":"https://v.daum.net/v/20220913122002657","retrieved":1663042499800},{"title":"'오겜' 황동혁·이정재, '에미상' 수상..비영어권 최초 '새역사' [74th ..","contents":"이데일리","link":"https://v.daum.net/v/20220913120320362","retrieved":1663042499802},{"title":"믿고 보는 정우x이유미..'멘탈코치 제갈길' 첫방부터 합격점","contents":"OSEN","link":"https://v.daum.net/v/20220913114014498","retrieved":1663042499812},{"title":"과연 정우는 짜고 치는 놈들을 싹 갈아엎을 수 있을까","contents":"엔터미디어","link":"https://v.daum.net/v/20220913112434792","retrieved":1663042499812},{"title":"\"플랜 비\" 외치면 웃음이 터진다.. 활기 책임지는 음문석 대활약 세가지","contents":"텐아시아","link":"https://v.daum.net/v/20220913112207701","retrieved":1663042499822},{"title":"이학주, 비연예인 여친과 오는 11월 결혼.. 품절남 된다","contents":"스포츠한국","link":"https://v.daum.net/v/20220913112019616","retrieved":1663042499826},{"title":"이학주, 11월 비연예인과 결혼","contents":"이데일리","link":"https://v.daum.net/v/20220913112004597","retrieved":1663042499827},{"title":"엑소 수호, '힙하게' 출연 확정..이민기·한지민 만난다","contents":"엑스포츠뉴스","link":"https://v.daum.net/v/20220913110506882","retrieved":1663042499827},{"title":"대세 이유미, 발가락 통증 감내하더니..'멘탈코치'로 이름값 증명","contents":"엑스포츠뉴스","link":"https://v.daum.net/v/20220913105009201","retrieved":1663042499828},{"title":"팬들이 골라준 옷이 드라마에? '미미쿠스', 메타버스 스타일링 입었다","contents":"OSEN","link":"https://v.daum.net/v/20220913104407004","retrieved":1663042499830},{"title":"박하나X오승아, '태풍의 신부' 확정..나란히 KBS 안방극장 복귀","contents":"마이데일리","link":"https://v.daum.net/v/20220913102035079","retrieved":1663042499832},{"title":"'오징어게임' 박해수·오영수, TV드라마 남우조연상 불발","contents":"이데일리","link":"https://v.daum.net/v/20220913093844329","retrieved":1663031427885},{"title":"첫방 '멘탈코치 제갈길' 정우, 이유미 부상 목격→인생 전환점 될까?","contents":"스포츠동아","link":"https://v.daum.net/v/20220913091912533","retrieved":1663031427886}]}