{"title":"다음 연예 ─ 뉴스 ─ 드라마","url":"https://entertain.daum.net/news/drama","favicon":"https://entertain.daum.net/news/favicon.ico","elements":[{"title":"유연석, 돌담 복귀 동시에 '위기'..안효섭에 경고 \"한석규, 목표가 돼선 안돼\"","contents":"OSEN","link":"https://v.daum.net/v/20230609234508204","retrieved":1686323395413},{"title":"\"손이 아니라 다른걸 잃을 수도\" 유연석, 안효섭X이성경과 갈등","contents":"MBC연예","link":"https://v.daum.net/v/20230609233959170","retrieved":1686323395414},{"title":"유연석, 컴백 후 첫 수술 환자 사망→안효섭·이성경과 갈등","contents":"엑스포츠뉴스","link":"https://v.daum.net/v/20230609232818100","retrieved":1686323395418},{"title":"유연석, 안효섭 보며 \"의사한테 중요한 연장은 칼 아니라 손...앞으로 재밌겠네\"","contents":"TV리포트","link":"https://v.daum.net/v/20230609232200036","retrieved":1686323395427},{"title":"'김사부3' 유연석 센터장 컴백..\"한석규가 목표 돼선 안돼\" 폭발","contents":"스타뉴스","link":"https://v.daum.net/v/20230609231508001","retrieved":1686323395428},{"title":"'김사부3' 유연석 \"돌담병원 비효율적\"→한석규 \"지켜보자\"","contents":"스타뉴스","link":"https://v.daum.net/v/20230609223144629","retrieved":1686319786427},{"title":"'김사부3' 유연석, 안효섭과 기싸움 \"여기서 볼 줄 몰랐는데...앞으로 재밌겠네\"","contents":"엑스포츠뉴스","link":"https://v.daum.net/v/20230609222959614","retrieved":1686319786427},{"title":"'낭만닥터 김사부3' 유연석, 돌담병원 컴백… \"원칙대로 시작해보겠다\"","contents":"MBC연예","link":"https://v.daum.net/v/20230609221759518","retrieved":1686319786434},{"title":"'김사부3' 이성경 \"유연석, 악으로 깡으로 유명했던 분\"","contents":"엑스포츠뉴스","link":"https://v.daum.net/v/20230609221403484","retrieved":1686319786438},{"title":"'김사부3' 유연석 컴백 \"여전히 이상한 돌담병원\" 의미심장","contents":"스타뉴스","link":"https://v.daum.net/v/20230609221214470","retrieved":1686316380237},{"title":"김태리의 간절한 절규 “또 시작됐다. 또 사람이 죽을 거다”","contents":"스포츠동아","link":"https://v.daum.net/v/20230609213324004","retrieved":1686316380243},{"title":"안은진 \"엄마 연기? 제가 애는 없지만\"…유쾌했던 '나쁜엄마'","contents":"엑스포츠뉴스","link":"https://v.daum.net/v/20230609213159984","retrieved":1686316380245},{"title":"'비밀의 여자' 서태양, 최윤영 걱정→최윤영, 깨어난 신고은 발견 '깜짝'","contents":"스타뉴스","link":"https://v.daum.net/v/20230609204856370","retrieved":1686313142988},{"title":"‘비밀의 여자’ 이선호, 최윤영에 직진 고백 “사랑해요”...깨어난 신고은 ‘충격’","contents":"TV리포트","link":"https://v.daum.net/v/20230609203201152","retrieved":1686313142989},{"title":"눈을 뗄 수 없는 ‘단짠커플’ 김동욱♥진기주의 심쿵 포인트","contents":"스포츠동아","link":"https://v.daum.net/v/20230609202153011","retrieved":1686313142990}]}