{"title":"다음 연예 ─ 뉴스 ─ 드라마","url":"https://entertain.daum.net/news/drama","favicon":"https://entertain.daum.net/news/favicon.ico","elements":[{"title":"뻔뻔한 박하나 \"여기서 우리 애 낳을 거다. 방 마련해달라\" 지현우에 선언","contents":"스포츠서울","link":"https://entertain.v.daum.net/v/20220227203101312","retrieved":1645964193658},{"title":"'신사와 아가씨' 이세희, 박하나 임신에 충격..지현우에 \"헤어지자\"","contents":"스타뉴스","link":"https://entertain.v.daum.net/v/20220227202352233","retrieved":1645964193659},{"title":"박하나 뻔뻔 \"임신 12주, 아이까지 부정하지 마\"","contents":"뉴스엔","link":"https://entertain.v.daum.net/v/20220227202249221","retrieved":1645964193666},{"title":"'신사와 아가씨' 이세희, 박하나 임신 알고 지현우와 이별 '분노'","contents":"엑스포츠뉴스","link":"https://entertain.v.daum.net/v/20220227202132205","retrieved":1645964193667},{"title":"'신사와아가씨' 박하나, 지현우에 돌직구 \"아이 여기서 기르고파\"","contents":"스타뉴스","link":"https://entertain.v.daum.net/v/20220227201842185","retrieved":1645964193667},{"title":"'신사와 아가씨' 박하나, 지현우 협박 \"회장님 아이 임신했다\"","contents":"엑스포츠뉴스","link":"https://entertain.v.daum.net/v/20220227200542059","retrieved":1645960186448},{"title":"진선규, 김남길 고뇌에 고뇌..빛나는 열연","contents":"스타뉴스","link":"https://entertain.v.daum.net/v/20220227195637972","retrieved":1645960186460},{"title":"박주미, 설득력 더한 '감정의 진폭'","contents":"스타뉴스","link":"https://entertain.v.daum.net/v/20220227190722517","retrieved":1645956774391},{"title":"박주미·전수경·이가령, 현실 리액션..\"매회가 떡밥\"","contents":"스타뉴스","link":"https://entertain.v.daum.net/v/20220227190232444","retrieved":1645956774392},{"title":"김혜수, 손예진에게 밀렸다..넷플릭스서 힘 못 쓰는 '소년심판'","contents":"텐아시아","link":"https://entertain.v.daum.net/v/20220227185402294","retrieved":1645956774394},{"title":"김남길,  촘촘하게 그려낸 인물의 내면 '믿보배'","contents":"스타뉴스","link":"https://entertain.v.daum.net/v/20220227185317288","retrieved":1645956774394},{"title":"\"착붙 캐릭터 소름\"..'사과→복귀' 서예지 바라보는 업계 시선은?","contents":"OSEN","link":"https://entertain.v.daum.net/v/20220227172934853","retrieved":1645953033008},{"title":"'스물다섯 스물하나' 김태리 vs 보나, 머리채 잡았다","contents":"마이데일리","link":"https://entertain.v.daum.net/v/20220227160831432","retrieved":1645945824872},{"title":"미디어의 긍정적 영향력이 발휘되어야 할 때 '소년심판'","contents":"MBC연예","link":"https://entertain.v.daum.net/v/20220227152757849","retrieved":1645945824872},{"title":"김태리-보나, 결국 머리채 잡고..철천지 원수됐다","contents":"뉴스엔","link":"https://entertain.v.daum.net/v/20220227151155495","retrieved":1645942361841}]}