{"title":"다음 연예 ─ 뉴스 ─ 드라마","url":"https://entertain.daum.net/news/drama","favicon":"https://entertain.daum.net/news/favicon.ico","elements":[{"title":"‘소옆경’ 측 “김래원 과거 순둥美 포착, 진돗개 된 결정적 사건 드러난다”","contents":"뉴스엔","link":"https://v.daum.net/v/20221207095016215","retrieved":1670374467631},{"title":"김아현, 세계적 모델 '완벽 비주얼'","contents":"스타뉴스","link":"https://v.daum.net/v/20221207095013212","retrieved":1670374467632},{"title":"\"주현영 내 딸이다\" 이서진, 회사에 부녀 관계 밝혔다 '위기'","contents":"엑스포츠뉴스","link":"https://v.daum.net/v/20221207094827150","retrieved":1670374467635},{"title":"'일당백집사' '집사커플' 이혜리♥이준영, 달콤한 로맨스 시작","contents":"OSEN","link":"https://v.daum.net/v/20221207094038843","retrieved":1670374467636},{"title":"정용화X차태현, 만나기만 하면 '으르렁'…'두뇌공조' 1월 2일 첫방","contents":"마이데일리","link":"https://v.daum.net/v/20221207093625695","retrieved":1670374467636},{"title":"\"시청률·화제성 1위\" 적수 없는 '재벌집', 신드롬 더 뜨겁게 타오른다","contents":"마이데일리","link":"https://v.daum.net/v/20221207092730381","retrieved":1670374467637},{"title":"“우리 헤어지자” 한지현, 배인혁에 깜짝 이별통보..위기 극복할까","contents":"OSEN","link":"https://v.daum.net/v/20221207092722372","retrieved":1670374467637},{"title":"오늘 공개 '커넥트', 관전 포인트 3","contents":"TV리포트","link":"https://v.daum.net/v/20221207092500276","retrieved":1670374467637},{"title":"'재벌집' 싹쓸이..3주째 TV 종합 1위·송중기 출연자 '화제성 1위'","contents":"스타뉴스","link":"https://v.daum.net/v/20221207091727017","retrieved":1670374467640},{"title":"설현, 눈물→주취 연기까지..입체적 열연 호평","contents":"OSEN","link":"https://v.daum.net/v/20221207091339899","retrieved":1670374467640},{"title":"시청자 홀린 ‘재벌집 막내아들’ 2막 입성 기념 미공개컷 공개","contents":"뉴스엔","link":"https://v.daum.net/v/20221207091129830","retrieved":1670374467641},{"title":"‘트롤리’ 김무열 첫 스틸 공개, 일잘알 수석보좌관 변신","contents":"뉴스엔","link":"https://v.daum.net/v/20221207090910761","retrieved":1670374467648},{"title":"송중기 다음은 이보영…국내 1위 광고 '대행사' 카리스마","contents":"OSEN","link":"https://v.daum.net/v/20221207090754707","retrieved":1670374467648},{"title":"‘슈룹’ 옥자연 “김해숙-김혜수와 함께 하는 행운 감사했다”","contents":"뉴스엔","link":"https://v.daum.net/v/20221207090414593","retrieved":1670374467648},{"title":"'재벌집 막내아들' 신드롬 이을까…'대행사' 이보영→조성하, 출격 준비 완료","contents":"마이데일리","link":"https://v.daum.net/v/20221207090354583","retrieved":1670374467649}]}