{"title":"다음 연예 ─ 뉴스 ─ 드라마","url":"https://entertain.daum.net/news/drama","favicon":"https://entertain.daum.net/news/favicon.ico","elements":[{"title":"장기용·천우희, ‘살롱드립2’ 출연…‘히어로는 아닙니다만’ 홍보 요정","contents":"스포츠동아","link":"https://v.daum.net/v/20240413080012153","retrieved":1712963288250},{"title":"'다리 절단' 황정음, 정체 발각 위기…엄기준, 메두사 존재 알았다","contents":"텐아시아","link":"https://v.daum.net/v/20240413075902112","retrieved":1712963288251},{"title":"차은우, 박혁권과 동반 투신 \"더는 김남주 건들지 마\"","contents":"엑스포츠뉴스","link":"https://v.daum.net/v/20240413075009083","retrieved":1712963288252},{"title":"김강우, 불륜 저지르고 子 살해범에 증거 넘겼다…김남주, 기자회견서 '폭로'","contents":"텐아시아","link":"https://v.daum.net/v/20240413073902963","retrieved":1712963288253},{"title":"'7인의 부활' 엄기준, 메두사 존재 알았다..황정음 정체 발각 위기","contents":"스타뉴스","link":"https://v.daum.net/v/20240413073418872","retrieved":1712963288254},{"title":"'원더풀 월드' 김남주-차은우, 서로에게 눈물 속죄..쌍방구원 뭉클","contents":"스타뉴스","link":"https://v.daum.net/v/20240413072918798","retrieved":1712963288256},{"title":"황정음, 엄기준에 ‘메두사’ 정체발각 위기","contents":"OSEN","link":"https://v.daum.net/v/20240413072617788","retrieved":1712963288258},{"title":"이유비, 황정음 살해 실패→엄기준에 뒷통수 맞았다","contents":"엑스포츠뉴스","link":"https://v.daum.net/v/20240413065003480","retrieved":1712959709301},{"title":"차은우, 김남주에 ‘눈물의 사죄’→박혁권 ‘살해 협박’..“죽여줄게”","contents":"OSEN","link":"https://v.daum.net/v/20240413064918474","retrieved":1712959709301},{"title":"김남주 \"子 뺑소니 진범=박혁권\" 폭로…차은우, 박혁권과 '투신'","contents":"마이데일리","link":"https://v.daum.net/v/20240413062806372","retrieved":1712959709301},{"title":"돌아온 '수사반장 1958'→넷플릭스 '종말의 바보' 제작발표회","contents":"서울경제","link":"https://v.daum.net/v/20240413060043006","retrieved":1712956165685},{"title":"'7인의 부활' 황정음, 엄기준이 판 함정에 빠진 이준 도왔다…'메두사' 정체 발각 위기","contents":"SBS연예뉴스","link":"https://v.daum.net/v/20240413032100427","retrieved":1712948926636},{"title":"'7인의 부활' 이준, \"걔도 내가 느꼈던 감정들 느끼고 있지 않을까\"…이유비 걱정","contents":"SBS연예뉴스","link":"https://v.daum.net/v/20240413025100257","retrieved":1712945460081},{"title":"“죽여줄게” 차은우, 난간에서 박혁권 살해 협박…“같이 가자”","contents":"MK스포츠","link":"https://v.daum.net/v/20240413024201233","retrieved":1712945460081},{"title":"김남주 \"진범은 박혁권\"…기자회견 위해 작가 복귀","contents":"엑스포츠뉴스","link":"https://v.daum.net/v/20240413014356118","retrieved":1712941845704}]}