{"title":"다음 연예 ─ 뉴스 ─ 드라마","url":"https://entertain.daum.net/news/drama","favicon":"https://entertain.daum.net/news/favicon.ico","elements":[{"title":"‘청춘월담’ 표예진, 털털 ‘남장’ 벗고 시선강탈 ‘꽃미모’ 뽐냈다..비하인드 스틸 공개","contents":"OSEN","link":"https://v.daum.net/v/20230321113120971","retrieved":1679368260488},{"title":"‘하트시그널4’ 안방 컴백… 채널A “5월 중 첫 방송 예정”","contents":"이데일리","link":"https://v.daum.net/v/20230321112349443","retrieved":1679368260488},{"title":"'오아시스', 전설의 드라마 '모래시계'와 설정 같은데 정서 다른 까닭","contents":"엔터미디어","link":"https://v.daum.net/v/20230321111920135","retrieved":1679368260489},{"title":"채널A 드라마플러스본부장 “시청률 부담 커, ‘가면의 여왕’ 기대 부탁”","contents":"뉴스엔","link":"https://v.daum.net/v/20230321111838090","retrieved":1679368260489},{"title":"\"귀신이 사랑하면 성불\"…방민아, 윤찬영 직진에도 냉랭","contents":"OSEN","link":"https://v.daum.net/v/20230321111816068","retrieved":1679368260489},{"title":"'센언니들 컴온!' 송혜교 이어 전도연·김희애·문소리·엄정화 온다","contents":"스포츠서울","link":"https://v.daum.net/v/20230321110802491","retrieved":1679368260490},{"title":"장동윤x주하윤, '오아시스' OST '체념' 가창…오늘 발매","contents":"OSEN","link":"https://v.daum.net/v/20230321110258206","retrieved":1679368260491},{"title":"'더 글로리' 정성일, 나이스 하도영! 영광 이끈 명품 열연","contents":"OSEN","link":"https://v.daum.net/v/20230321105457683","retrieved":1679364160927},{"title":"'청춘월담' 박형식, 직진 고백 \"온 힘을 다해 지킬 것이다\"···깊어지는 로맨스 서사","contents":"서울경제","link":"https://v.daum.net/v/20230321105002435","retrieved":1679364160928},{"title":"'판도라' 한수연 \"헝가리語도 할줄 안다고?\"…亞배우 유일 헝가리語 능력자","contents":"스포츠조선","link":"https://v.daum.net/v/20230321104251133","retrieved":1679364160928},{"title":"윤찬영, 좋아한다던 방민아와 뜬금 냉전 “오히려 엇갈리기 시작”","contents":"뉴스엔","link":"https://v.daum.net/v/20230321104109073","retrieved":1679364160928},{"title":"유인나 \"뼈아픈 팩폭 날린다\"…'연플루언서' 변신","contents":"마이데일리","link":"https://v.daum.net/v/20230321103911984","retrieved":1679364160928},{"title":"조아람, 드라마 '닥터 차정숙' 전격 발탁! 엄정화 만난다","contents":"스타뉴스","link":"https://v.daum.net/v/20230321103748938","retrieved":1679364160928},{"title":"'더 글로리' 혜정이 맞아? 차주영, 이세계 神 레드린으로 변신","contents":"마이데일리","link":"https://v.daum.net/v/20230321103421762","retrieved":1679364160930},{"title":"이세영, '열녀박씨 계약결혼뎐' 출연…'옷소매' 열풍 잇는다","contents":"엑스포츠뉴스","link":"https://v.daum.net/v/20230321103214663","retrieved":1679364160931}]}