{"title":"다음 연예 ─ 뉴스 ─ 드라마","url":"https://entertain.daum.net/news/drama","favicon":"https://entertain.daum.net/news/favicon.ico","elements":[{"title":"'미녀와 순정남' 고윤, 한수아 병문안 온 지현우 문전 박대 \"어디라고 들어와\"","contents":"엑스포츠뉴스","link":"https://v.daum.net/v/20240721200716446","retrieved":1721560175602},{"title":"“가슴 아픈 운명”…임수향·지현우, 엇갈린 로맨스","contents":"MK스포츠","link":"https://v.daum.net/v/20240721195101108","retrieved":1721560175602},{"title":"장나라, ♥연하 남편 덕 보네…'인생 짝꿍' 안목에 일이 다시 술술","contents":"텐아시아","link":"https://v.daum.net/v/20240721192902794","retrieved":1721560175602},{"title":"최진혁, 불안한 정은지 달래는 포옹…러브라인 급물살","contents":"엑스포츠뉴스","link":"https://v.daum.net/v/20240721171041537","retrieved":1721549581969},{"title":"'거인의 어깨' 첫 강연 주자는 뮤지컬 음악감독 김문정","contents":"이데일리","link":"https://v.daum.net/v/20240721170623440","retrieved":1721549581975},{"title":"'감사합니다' 명품조연 릴레이 특별출연..조한철도 눈도장","contents":"OSEN","link":"https://v.daum.net/v/20240721164605869","retrieved":1721549581978},{"title":"지현우, 돈으로 엮인 임수향-고윤 관계 의심 시작","contents":"뉴스엔","link":"https://v.daum.net/v/20240721160635837","retrieved":1721545826188},{"title":"임수향, 이미 남친 생겼는데…지현우, 미련 못 버렸다","contents":"텐아시아","link":"https://v.daum.net/v/20240721160301703","retrieved":1721545826189},{"title":"신하균X진구 비상사태, JU건설 내 분신 시도 발생","contents":"뉴스엔","link":"https://v.daum.net/v/20240721160118626","retrieved":1721545826191},{"title":"임수향X지현우, 한밤중 애틋 대화 ‘엇갈린 로맨스’","contents":"스포츠동아","link":"https://v.daum.net/v/20240721154941291","retrieved":1721545826193},{"title":"'미녀와 순정남' 지현우, 고윤 만나는 임수향 붙잡았다","contents":"이데일리","link":"https://v.daum.net/v/20240721154101063","retrieved":1721545826206},{"title":"신하균, 현장식당 운영권 비리 정황 포착…최고 시청률 7.5%","contents":"뉴스엔","link":"https://v.daum.net/v/20240721152047530","retrieved":1721545826206},{"title":"150만 유튜버 랄랄, 엄마 됐다…3.7kg 딸 출산","contents":"이데일리","link":"https://v.daum.net/v/20240721151539361","retrieved":1721545826208},{"title":"'이혼' 이동건 \"연애, 아이 생각하면 아직 해선 안 돼\"","contents":"이데일리","link":"https://v.daum.net/v/20240721145738925","retrieved":1721542460559},{"title":"돈키호테 신하균만? 판 짠 정문성과의 대결구도도 기대되는 이유","contents":"엔터미디어","link":"https://v.daum.net/v/20240721144643765","retrieved":1721542460559}]}