{"title":"다음 연예 ─ 뉴스 ─ 드라마","url":"https://entertain.daum.net/news/drama","favicon":"https://entertain.daum.net/news/favicon.ico","elements":[{"title":"최우식X손석구 '살인자ㅇ난감', 어떻게 실사화 했나…\"캐릭터가 곧 장르\"","contents":"엑스포츠뉴스","link":"https://v.daum.net/v/20240207134700844","retrieved":1707282631596},{"title":"'연애 지상주의 구역' 이태빈→오민수 \"덕분에 따뜻한 나날 보내\" 종영 소감","contents":"OSEN","link":"https://v.daum.net/v/20240207134413780","retrieved":1707282631606},{"title":"'내남결' 송하윤도 참 대단하다","contents":"OSEN","link":"https://v.daum.net/v/20240207133248479","retrieved":1707282631606},{"title":"'킬러들의 쇼핑몰' 김혜준 \"작은 일엔 긴장, 오히려 큰일은 덤덤한 편\"","contents":"OSEN","link":"https://v.daum.net/v/20240207131120061","retrieved":1707279144286},{"title":"보아가 거기서 왜 나와?...'내남결' 제작진의 안타까운 무리수","contents":"엔터미디어","link":"https://v.daum.net/v/20240207131006026","retrieved":1707279144287},{"title":"김혜준 \"액션, 모든 장면 힘들어…장르물 말고 로코 하고파\"","contents":"엑스포츠뉴스","link":"https://v.daum.net/v/20240207130747976","retrieved":1707279144287},{"title":"'킬쇼' 김혜준 \"장르물 안 하려 했는데…난 어쩔 수 없는 듯\"","contents":"스포츠조선","link":"https://v.daum.net/v/20240207130706962","retrieved":1707279144288},{"title":"냉혈한 임금 조정석 곁을 지키는 유일한 벗, 강홍석 충심+소신 직언 ‘열연’","contents":"뉴스엔","link":"https://v.daum.net/v/20240207124625444","retrieved":1707279144288},{"title":"'킬러들의 쇼핑몰' 김혜준 \"액션 힘들어..이젠 귀여움 보여줄 때 됐다\"","contents":"OSEN","link":"https://v.daum.net/v/20240207124118365","retrieved":1707279144291},{"title":"안하무인 빌런 보아, 악마 본색 드러내고 이이경 유혹 “박민영 꼭 죽여줄래”","contents":"뉴스엔","link":"https://v.daum.net/v/20240207123950335","retrieved":1707279144292},{"title":"'킬러들의 쇼핑몰' 김혜준 \"이동욱, 츤데레 끝판왕..너무 멋있어\"","contents":"OSEN","link":"https://v.daum.net/v/20240207121116828","retrieved":1707275492357},{"title":"\"오늘 팝콘각이다\" 이지아, '전남친' 강기영·'전남편' 오민석 삼자대면","contents":"OSEN","link":"https://v.daum.net/v/20240207113053015","retrieved":1707275492361},{"title":"이영은, '미녀와 순정남'으로 안방 컴백..지현우 늦둥이 고모役","contents":"스타뉴스","link":"https://v.daum.net/v/20240207112949936","retrieved":1707275492362},{"title":"‘밤이 되었습니다’ 웹소설로 재탄생, 학기 초 이야기 담긴다","contents":"뉴스엔","link":"https://v.daum.net/v/20240207111736327","retrieved":1707275492362},{"title":"'내남결' 최규리, 리얼 연기 끝판왕..'대세 청춘 배우' 등극","contents":"스타뉴스","link":"https://v.daum.net/v/20240207111700298","retrieved":1707275492362}]}