{"title":"다음 연예 ─ 뉴스 ─ 드라마","url":"https://entertain.daum.net/news/drama","favicon":"https://entertain.daum.net/news/favicon.ico","elements":[{"title":"김미숙, 제주도 찾아온 조윤서에 “내 딸이 그 꼴 당했는데 안 미치냐” 분노","contents":"MBC연예","link":"https://v.daum.net/v/20240107234556535","retrieved":1704640184058},{"title":"'삼달리' 지창욱, 신혜선 폭행영상 유출에 분노 \"왜 맞고만 있어?\"","contents":"TV리포트","link":"https://v.daum.net/v/20240107234530534","retrieved":1704640184060},{"title":"김동준, 사산한 이시아에 \"황후가 가장 소중…날 보고 견뎌달라\" 위로","contents":"엑스포츠뉴스","link":"https://v.daum.net/v/20240107233903488","retrieved":1704640184060},{"title":"신혜선 '갑질 영상' 주작한 조윤서, \"심심해서 올렸다\" 뻔뻔","contents":"텐아시아","link":"https://v.daum.net/v/20240107233802484","retrieved":1704640184061},{"title":"'삼달리' 지창욱, ♥신혜선에 애정 폭발 \"예쁘지를 말든가\"","contents":"스타뉴스","link":"https://v.daum.net/v/20240107232738465","retrieved":1704640184061},{"title":"이영애와 이혼…김영재, 이시원과도 파국 \"친권행사하기 전에 떠나라\"","contents":"텐아시아","link":"https://v.daum.net/v/20240107230010379","retrieved":1704636524522},{"title":"김동준 \"나도 백성 버리고 도망쳤다…아무도 벌하지 않을 것\" 선언","contents":"엑스포츠뉴스","link":"https://v.daum.net/v/20240107225520347","retrieved":1704636524526},{"title":"이영애, 독극물 범인=남편 ‘확신’..김영재, 괴한 습격 받았다","contents":"OSEN","link":"https://v.daum.net/v/20240107224039264","retrieved":1704636524526},{"title":"'마에스트라' 이영애, 독극물 먹인 범인으로 김영재 확신 \"증거도 갖고 있어\"","contents":"TV리포트","link":"https://v.daum.net/v/20240107223700251","retrieved":1704636524530},{"title":"이영애, 이혼 발표→김영재 괴한 습격…이무생이 나섰나","contents":"엑스포츠뉴스","link":"https://v.daum.net/v/20240107223658250","retrieved":1704636524530},{"title":"'효심이네' 정영숙, 하준♥유이 연애 사실 알았다 '충격'","contents":"스타뉴스","link":"https://v.daum.net/v/20240107223340241","retrieved":1704636524532},{"title":"김동준, 불탄 장전 앞에서 최수종과 오열 “나도 백성을 버리고 도망쳤소”","contents":"OSEN","link":"https://v.daum.net/v/20240107223202227","retrieved":1704636524532},{"title":"'불륜녀' 이시원 질투심 폭발, 이영애 사표 반대에 \"너무 이기적인 생각\"","contents":"텐아시아","link":"https://v.daum.net/v/20240107221802144","retrieved":1704636524535},{"title":"'불륜녀' 이시원, 임신 고백했다…김영재 \"여기 떠나\"","contents":"엑스포츠뉴스","link":"https://v.daum.net/v/20240107221631127","retrieved":1704636524535},{"title":"지승현, 온몸에 화살 박힌채 死... \"피투성이+치아로 활 당겨\"","contents":"OSEN","link":"https://v.daum.net/v/20240107220303040","retrieved":1704633084237}]}